README.md
setup.py
pyhpweb/__init__.py
pyhpweb/client.py
pyhpweb/constant.py
pyhpweb/error.py
pyhpweb/log.py
pyhpweb/pyhp.py
pyhpweb/tools.py
pyhpweb.egg-info/PKG-INFO
pyhpweb.egg-info/SOURCES.txt
pyhpweb.egg-info/dependency_links.txt
pyhpweb.egg-info/requires.txt
pyhpweb.egg-info/top_level.txt