Metadata-Version: 2.1
Name: pyhpweb
Version: 0.1.1
Summary: Web 服务端，在请求页面时后端执行 Html 文件中的 Python 代码生成动态网页 （类似 PHP）
Home-page: https://github.com/FengLiuFeseliud/PyHP-web
Author: FengLiuFeseliud
Author-email: 17351198406@qq.com
License: UNKNOWN
Keywords: web,server,html,Hypertext-Preprocessor
Platform: any
Classifier: Programming Language :: Python :: 3
Classifier: License :: OSI Approved :: MIT License
Classifier: Operating System :: OS Independent
Requires-Python: >=3.9
